odoo/addons/purchase_fully_received/README.rst
odoo/addons/purchase_fully_received/__init__.py
odoo/addons/purchase_fully_received/__manifest__.py
odoo/addons/purchase_fully_received/i18n/purchase_fully_received.pot
odoo/addons/purchase_fully_received/models/__init__.py
odoo/addons/purchase_fully_received/models/purchase.py
odoo/addons/purchase_fully_received/readme/CONTRIBUTORS.rst
odoo/addons/purchase_fully_received/readme/DESCRIPTION.rst
odoo/addons/purchase_fully_received/readme/USAGE.rst
odoo/addons/purchase_fully_received/static/description/icon.png
odoo/addons/purchase_fully_received/static/description/index.html
odoo/addons/purchase_fully_received/tests/__init__.py
odoo/addons/purchase_fully_received/tests/test_purchase_fully_received.py
odoo/addons/purchase_fully_received/views/purchase_views.xml
odoo_addon_purchase_fully_received-16.0.1.0.0.2.dist-info/METADATA
odoo_addon_purchase_fully_received-16.0.1.0.0.2.dist-info/WHEEL
odoo_addon_purchase_fully_received-16.0.1.0.0.2.dist-info/top_level.txt
odoo_addon_purchase_fully_received-16.0.1.0.0.2.dist-info/RECORD
